aliyunsdkververica/__init__.py
aliyunsdkververica/endpoint.py
aliyunsdkververica/request/__init__.py
aliyunsdkververica/request/v20200501/CreateDeploymentRequest.py
aliyunsdkververica/request/v20200501/CreateSavepointRequest.py
aliyunsdkververica/request/v20200501/CreateUdfArtifactRequest.py
aliyunsdkververica/request/v20200501/DatabaseExistsRequest.py
aliyunsdkververica/request/v20200501/DeleteArtifactRequest.py
aliyunsdkververica/request/v20200501/DeleteDeploymentRequest.py
aliyunsdkververica/request/v20200501/DeleteUdfArtifactRequest.py
aliyunsdkververica/request/v20200501/ExecuteSqlScriptRequest.py
aliyunsdkververica/request/v20200501/ExecuteSqlscriptsStatementsRequest.py
aliyunsdkververica/request/v20200501/FunctionExistsRequest.py
aliyunsdkververica/request/v20200501/GetArtifactMetadataRequest.py
aliyunsdkververica/request/v20200501/GetCatalogRequest.py
aliyunsdkververica/request/v20200501/GetDatabaseRequest.py
aliyunsdkververica/request/v20200501/GetDefaultDatabaseRequest.py
aliyunsdkververica/request/v20200501/GetDeploymentDefaultsRequest.py
aliyunsdkververica/request/v20200501/GetDeploymentRequest.py
aliyunsdkververica/request/v20200501/GetFunctionRequest.py
aliyunsdkververica/request/v20200501/GetGlobalDeploymentDefaultsRequest.py
aliyunsdkververica/request/v20200501/GetTableRequest.py
aliyunsdkververica/request/v20200501/GetUdfArtifactRequest.py
aliyunsdkververica/request/v20200501/ListArtifactsRequest.py
aliyunsdkververica/request/v20200501/ListCatalogsRequest.py
aliyunsdkververica/request/v20200501/ListDatabasesRequest.py
aliyunsdkververica/request/v20200501/ListDeploymentTargetsRequest.py
aliyunsdkververica/request/v20200501/ListDeploymentsRequest.py
aliyunsdkververica/request/v20200501/ListFlinkVersionsRequest.py
aliyunsdkververica/request/v20200501/ListFunctionsRequest.py
aliyunsdkververica/request/v20200501/ListJobsRequest.py
aliyunsdkververica/request/v20200501/ListNamespacesRequest.py
aliyunsdkververica/request/v20200501/ListSavepointsRequest.py
aliyun_python_sdk_ververica-1.0.2.dist-info/LICENSE
aliyun_python_sdk_ververica-1.0.2.dist-info/METADATA
aliyun_python_sdk_ververica-1.0.2.dist-info/WHEEL
aliyun_python_sdk_ververica-1.0.2.dist-info/top_level.txt
aliyun_python_sdk_ververica-1.0.2.dist-info/RECORD
